aliyunsdkvoicenavigator/__init__.py
aliyunsdkvoicenavigator/endpoint.py
aliyunsdkvoicenavigator/request/__init__.py
aliyunsdkvoicenavigator/request/v20180612/AssociateChatbotInstanceRequest.py
aliyunsdkvoicenavigator/request/v20180612/AuditTTSVoiceRequest.py
aliyunsdkvoicenavigator/request/v20180612/BeginDialogueRequest.py
aliyunsdkvoicenavigator/request/v20180612/CollectedNumberRequest.py
aliyunsdkvoicenavigator/request/v20180612/CreateDownloadUrlRequest.py
aliyunsdkvoicenavigator/request/v20180612/CreateInstanceRequest.py
aliyunsdkvoicenavigator/request/v20180612/DebugBeginDialogueRequest.py
aliyunsdkvoicenavigator/request/v20180612/DebugCollectedNumberRequest.py
aliyunsdkvoicenavigator/request/v20180612/DebugDialogueRequest.py
aliyunsdkvoicenavigator/request/v20180612/DeleteInstanceRequest.py
aliyunsdkvoicenavigator/request/v20180612/DescribeConversationContextRequest.py
aliyunsdkvoicenavigator/request/v20180612/DescribeConversationRequest.py
aliyunsdkvoicenavigator/request/v20180612/DescribeExportProgressRequest.py
aliyunsdkvoicenavigator/request/v20180612/DescribeInstanceRequest.py
aliyunsdkvoicenavigator/request/v20180612/DescribeNavigationConfigRequest.py
aliyunsdkvoicenavigator/request/v20180612/DescribeRecordingRequest.py
aliyunsdkvoicenavigator/request/v20180612/DescribeStatisticalDataRequest.py
aliyunsdkvoicenavigator/request/v20180612/DescribeTTSConfigRequest.py
aliyunsdkvoicenavigator/request/v20180612/DialogueRequest.py
aliyunsdkvoicenavigator/request/v20180612/DisableInstanceRequest.py
aliyunsdkvoicenavigator/request/v20180612/EnableInstanceRequest.py
aliyunsdkvoicenavigator/request/v20180612/EndDialogueRequest.py
aliyunsdkvoicenavigator/request/v20180612/ExportConversationDetailsRequest.py
aliyunsdkvoicenavigator/request/v20180612/ExportStatisticalDataRequest.py
aliyunsdkvoicenavigator/request/v20180612/GenerateUploadUrlRequest.py
aliyunsdkvoicenavigator/request/v20180612/GetAsrConfigRequest.py
aliyun_python_sdk_voicenavigator-1.7.0.dist-info/LICENSE
aliyun_python_sdk_voicenavigator-1.7.0.dist-info/METADATA
aliyun_python_sdk_voicenavigator-1.7.0.dist-info/WHEEL
aliyun_python_sdk_voicenavigator-1.7.0.dist-info/top_level.txt
aliyun_python_sdk_voicenavigator-1.7.0.dist-info/RECORD
